aloha/__init__.py
aloha/_version.py
aloha/base.py
aloha/settings.py
aloha/config/__init__.py
aloha/config/hocon.py
aloha/config/paths.py
aloha/db/__init__.py
aloha/db/base.py
aloha/db/duckdb.py
aloha/db/elasticsearch.py
aloha/db/kafka.py
aloha/db/mongo.py
aloha/db/mysql.py
aloha/db/oracle.py
aloha/db/postgres.py
aloha/db/redis.py
aloha/db/sqlite.py
aloha/encrypt/__init__.py
aloha/encrypt/aes.py
aloha/encrypt/hash.py
aloha/encrypt/jwt.py
aloha/encrypt/rsa.py
aloha/encrypt/vault/__init__.py
aloha/encrypt/vault/base.py
aloha/encrypt/vault/cyberark.py
aloha/encrypt/vault/plain.py
aloha/logger/__init__.py
aloha/logger/handler.py
aloha/logger/logger.py
aloha/script/__init__.py
aloha/script/base.py
aloha/script/compile.py
aloha/script/info.py
aloha/script/start.py
aloha/service/__init__.py
aloha/service/app.py
aloha/service/web.py
aloha/service/api/__init__.py
aloha/service/api/v0.py
aloha/service/api/v1.py
aloha/service/api/v2.py
aloha/service/http/__init__.py
aloha/service/http/base_api_client.py
aloha/service/http/base_api_handler.py
aloha/service/http/files.py
aloha/service/http/plain_http_handler.py
aloha/service/openapi/__init__.py
aloha/service/openapi/client.py
aloha/testing/__init__.py
aloha/testing/service_v1.py
aloha/testing/service_v2.py
aloha/testing/unit.py
aloha/times/__init__.py
aloha/times/timeout_async.py
aloha/times/timeout_asyncio.py
aloha/times/timeout_signal.py
aloha/util/__init__.py
aloha/util/html.py
aloha/util/json.py
aloha/util/random.py
aloha/util/sys_cuda.py
aloha/util/sys_gpu.py
aloha/util/sys_info.py
aloha-2025.1224.1646.dist-info/METADATA
aloha-2025.1224.1646.dist-info/WHEEL
aloha-2025.1224.1646.dist-info/entry_points.txt
aloha-2025.1224.1646.dist-info/top_level.txt
aloha-2025.1224.1646.dist-info/RECORD
